LICENSE
README.md
setup.cfg
setup.py
mixer_pyaudio.egg-info/PKG-INFO
mixer_pyaudio.egg-info/SOURCES.txt
mixer_pyaudio.egg-info/dependency_links.txt
mixer_pyaudio.egg-info/requires.txt
mixer_pyaudio.egg-info/top_level.txt
pyaudio_mixer/__init__.py
pyaudio_mixer/exceptions.py
pyaudio_mixer/input.py
pyaudio_mixer/mixer.py
pyaudio_mixer/output.py
pyaudio_mixer/utils.py