Metadata-Version: 2.1
Name: mixer-pyaudio
Version: 1.0
Summary: Audio mixing simplified.
Home-page: https://github.com/bossauh/pyaudiomixer
Download-URL: https://github.com/bossauh/pyaudiomixer/archive/refs/tags/v_10.tar.gz
Author: Philippe Mathew
Author-email: philmattdev@gmail.com
License: MIT
Keywords: audio,mixer,mixing,tool
Classifier: Development Status :: 5 - Production/Stable
Classifier: Intended Audience :: Developers
Classifier: Topic :: Software Development :: Build Tools
Classifier: License :: OSI Approved :: MIT License
Classifier: Programming Language :: Python :: 3.6
Classifier: Programming Language :: Python :: 3.7
License-File: LICENSE
